spotifetch/__init__.py
spotifetch/cli.py
spotifetch/fetch.py
spotifetch/helpers.py
spotifetch-0.4.4.dist-info/LICENSE
spotifetch-0.4.4.dist-info/WHEEL
spotifetch-0.4.4.dist-info/entry_points.txt
spotifetch-0.4.4.dist-info/METADATA
spotifetch-0.4.4.dist-info/RECORD
