Metadata-Version: 2.1
Name: spotifetch
Version: 0.4.4
Summary: A fetch tool for Spotify
License: MIT
Author: dotzenith
Requires-Python: >=3.9,<4.0
Classifier: License :: OSI Approved :: MIT License
Classifier: Programming Language :: Python :: 3
Classifier: Programming Language :: Python :: 3.9
Classifier: Programming Language :: Python :: 3.10
Classifier: Programming Language :: Python :: 3.11
Requires-Dist: appdirs (>=1.4.4,<2.0.0)
Requires-Dist: colorgram.py (>=1.2.0,<2.0.0)
Requires-Dist: kolorz (>=0.2.4,<0.3.0)
Requires-Dist: requests (>=2.28.2,<3.0.0)
Requires-Dist: spotipy (>=2.22.1,<3.0.0)
Requires-Dist: typer (>=0.7.0,<0.8.0)
